mpd_parser/__init__.py
mpd_parser/attribute_parsers.py
mpd_parser/constants.py
mpd_parser/exceptions.py
mpd_parser/parser.py
mpd_parser/timeline_utils.py
mpd_parser/models/__init__.py
mpd_parser/models/base_tags.py
mpd_parser/models/composite_tags.py
mpd_parser/models/segment_tags.py
mpd_parser-0.1.6.dist-info/licenses/LICENSE
mpd_parser-0.1.6.dist-info/METADATA
mpd_parser-0.1.6.dist-info/WHEEL
mpd_parser-0.1.6.dist-info/top_level.txt
mpd_parser-0.1.6.dist-info/RECORD
