Metadata-Version: 2.4
Name: mpd-parser
Version: 0.1.6
Summary: lxml based parser for DASH manifests (mpd files)
Home-page: https://github.com/avishaycohen/mpd-parser
Author: Avishay Cohen
Author-email: Avishay Cohen <avishay.c@gmail.com>
License: MIT License
Project-URL: Homepage, https://github.com/avishaycohen/mpd-parser
Keywords: parser,DASH,manifest,video,files
Classifier: License :: OSI Approved :: MIT License
Classifier: Programming Language :: Python
Classifier: Programming Language :: Python :: 3
Requires-Python: >=3.8
License-File: LICENSE
Requires-Dist: lxml
Requires-Dist: isodate
Provides-Extra: dev
Requires-Dist: pylint; extra == "dev"
Requires-Dist: pytest; extra == "dev"
Requires-Dist: mpegdash; extra == "dev"
Dynamic: license-file
